RsCmwWlanMeas/RsCmwWlanMeas.py
RsCmwWlanMeas/__init__.py
RsCmwWlanMeas/enums.py
RsCmwWlanMeas/repcap.py
RsCmwWlanMeas/CustomFiles/__init__.py
RsCmwWlanMeas/CustomFiles/events.py
RsCmwWlanMeas/CustomFiles/reliability.py
RsCmwWlanMeas/CustomFiles/utilities.py
RsCmwWlanMeas/Implementations/__init__.py
RsCmwWlanMeas/Implementations/Configure/Mimo.py
RsCmwWlanMeas/Implementations/Configure/Smimo.py
RsCmwWlanMeas/Implementations/Configure/__init__.py
RsCmwWlanMeas/Implementations/Configure/Isignal/Ofdm.py
RsCmwWlanMeas/Implementations/Configure/Isignal/__init__.py
RsCmwWlanMeas/Implementations/Configure/Isignal/Dsss/Elength.py
RsCmwWlanMeas/Implementations/Configure/Isignal/Dsss/__init__.py
RsCmwWlanMeas/Implementations/Configure/Isignal/Tdata/File.py
RsCmwWlanMeas/Implementations/Configure/Isignal/Tdata/__init__.py
RsCmwWlanMeas/Implementations/Configure/MultiEval/PowerVsTime.py
RsCmwWlanMeas/Implementations/Configure/MultiEval/Result.py
RsCmwWlanMeas/Implementations/Configure/MultiEval/Scount.py
RsCmwWlanMeas/Implementations/Configure/MultiEval/SpectrFlatness.py
RsCmwWlanMeas/Implementations/Configure/MultiEval/TsMask.py
RsCmwWlanMeas/Implementations/Configure/MultiEval/__init__.py
RsCmwWlanMeas/Implementations/Configure/MultiEval/Compensation/EfTaps.py
RsCmwWlanMeas/Implementations/Configure/MultiEval/Compensation/SkipSymbols.py
RsCmwWlanMeas/Implementations/Configure/MultiEval/Compensation/Tracking.py
RsCmwWlanMeas/Implementations/Configure/MultiEval/Compensation/__init__.py
RsCmwWlanMeas/Implementations/Configure/MultiEval/Demod/Fft.py
RsCmwWlanMeas/Implementations/Configure/MultiEval/Demod/__init__.py
RsCmwWlanMeas/Implementations/Configure/MultiEval/Limit/PowerVsTime.py
RsCmwWlanMeas/Implementations/Configure/MultiEval/Limit/__init__.py
RsCmwWlanMeas/Implementations/Configure/MultiEval/Limit/Modulation/Dsss.py
RsCmwWlanMeas/Implementations/Configure/MultiEval/Limit/Modulation/Lofdm.py
RsCmwWlanMeas/Implementations/Configure/MultiEval/Limit/Modulation/Pofdm.py
RsCmwWlanMeas-4.0.140.dist-info/METADATA
RsCmwWlanMeas-4.0.140.dist-info/WHEEL
RsCmwWlanMeas-4.0.140.dist-info/top_level.txt
RsCmwWlanMeas-4.0.140.dist-info/RECORD
